README.md
setup.py
bin/comparem
comparem/PCoA.py
comparem/VERSION
comparem/__init__.py
comparem/aai_calculator.py
comparem/amino_acid_usage.py
comparem/classify.py
comparem/codon_usage.py
comparem/hierarchical_clustering.py
comparem/kmer_usage.py
comparem/lgt_codon.py
comparem/lgt_dinucleotide.py
comparem/main.py
comparem/similarity_search.py
comparem.egg-info/PKG-INFO
comparem.egg-info/SOURCES.txt
comparem.egg-info/dependency_links.txt
comparem.egg-info/requires.txt
comparem.egg-info/top_level.txt
comparem/plots/__init__.py
comparem/plots/heatmap.py
comparem/plots/mpld3_plugins.py