Metadata-Version: 1.0
Name: comparem
Version: 0.1.2
Summary: A toolbox for comparative genomics.
Home-page: http://pypi.python.org/pypi/comparem/
Author: Donovan Parks
Author-email: donovan.parks@gmail.com
License: GPL3
Platform: UNKNOWN
